cog2/__init__.py
cog2/base.yaml
cog2/main.py
cog2-0.2.6.dist-info/METADATA
cog2-0.2.6.dist-info/WHEEL
cog2-0.2.6.dist-info/entry_points.txt
cog2-0.2.6.dist-info/RECORD
